GT_521F52/GT_521F52.py
GT_521F52/packets.py
GT_521F52-1.0.0.dist-info/LICENSE
GT_521F52-1.0.0.dist-info/METADATA
GT_521F52-1.0.0.dist-info/WHEEL
GT_521F52-1.0.0.dist-info/top_level.txt
GT_521F52-1.0.0.dist-info/RECORD
