Metadata-Version: 2.1
Name: GT-521F52
Version: 1.0.0
Summary: Python ADH-Tech GT521F52 library
Home-page: https://github.com/CESARBR/GT521F52
Author: Lucas Costa Cabral
Author-email: lcc2@cesar.org.br
License: Apache-2.0
Keywords: GT521F52,fingerprint,python
Platform: UNKNOWN
Classifier: Development Status :: 5 - Production/Stable
Classifier: Intended Audience :: Developers
Classifier: License :: OSI Approved :: Apache Software License
Classifier: Natural Language :: English
Classifier: Programming Language :: Python :: 3
Classifier: Programming Language :: Python :: 3.4
Classifier: Programming Language :: Python :: 3.5
Classifier: Programming Language :: Python :: 3.6
Requires-Dist: pyserial (>=3.4.0)
